{
  "asOf": "2026-04-21",
  "prices": {
    "PLTR": 146.07,
    "OSTX": 1.35,
    "LPTH": 14.07,
    "CISO": 0.310199,
    "FSLR": 186.4,
    "LMB": 94.76,
    "MTZ": 370.515,
    "INDB": 77.57,
    "TSLA": 386.675,
    "INTR": 8.12,
    "ATAT": 38.33,
    "FLUT": 109.0,
    "MU": 449.06,
    "FR": 63.43,
    "WELL": 206.18,
    "CTRE": 38.39,
    "SCHG": 32.3299,
    "QQQ": 643.39,
    "VOO": 647.36,
    "IBIT": 42.515,
    "VTI": 347.7,
    "RAND": 10.89,
    "PLMR": 131.73,
    "NVDA": 199.72,
    "UNH": 347.555,
    "VCTR": 74.32,
    "VEEV": 167.605,
    "EVR": 354.605,
    "FUTU": 162.81,
    "NFLX": 92.645,
    "HOOD": 86.53,
    "MELI": 1853.765,
    "TTWO": 217.26,
    "PSKY": 11.675,
    "PGR": 207.98,
    "SPOT": 524.65,
    "WMT": 129.46,
    "BETZ": 19.33,
    "VOOG": 76.23,
    "IAU": 88.07,
    "KGC": 32.2,
    "XSMO": 84.44,
    "SOFI": 18.775,
    "GOOGL": 332.3,
    "V": 309.41,
    "UBER": 77.24,
    "MSFT": 424.11,
    "HD": 344.21,
    "SMH": 463.46,
    "APLD": 31.402,
    "RGTI": 18.32,
    "AIQ": 53.675,
    "VRT": 313.92,
    "QTUM": 128.04,
    "ANET": 172.53,
    "CRDO": 181.31,
    "QBTS": 20.41,
    "SE": 87.075,
    "DFAE": 37.06,
    "DFAU": 48.765
  },
  "missing": [
    "LITM",
    "LITM",
    "PSTG",
    "PSTG",
    "PSTG",
    "PSTG",
    "PSTG",
    "PSTG"
  ]
}