{
  "asOf": "2026-04-15",
  "prices": {
    "PLTR": 142.27,
    "OSTX": 1.405,
    "LPTH": 13.845,
    "CISO": 0.356999,
    "FSLR": 194.92,
    "LMB": 88.48,
    "MTZ": 364.175,
    "INDB": 79.5201,
    "TSLA": 394.46,
    "INTR": 8.395,
    "ATAT": 36.895,
    "FLUT": 112.07,
    "MU": 453.51,
    "FR": 61.12,
    "WELL": 210.38,
    "CTRE": 39.63,
    "SCHG": 32.075,
    "QQQ": 636.67,
    "VOO": 643.114,
    "IBIT": 42.53,
    "VTI": 345.06,
    "RAND": 10.97,
    "PLMR": 130.13,
    "NVDA": 198.215,
    "UNH": 314.36,
    "VCTR": 72.945,
    "VEEV": 167.9,
    "EVR": 357.79,
    "PSTG": 64.935,
    "FUTU": 164.68,
    "NFLX": 107.275,
    "HOOD": 87.33,
    "MELI": 1877.78,
    "TTWO": 214.9,
    "PSKY": 11.695,
    "PGR": 201.82,
    "SPOT": 531.3852,
    "WMT": 124.825,
    "BETZ": 19.125,
    "VOOG": 455.05,
    "IAU": 90.295,
    "KGC": 33.365,
    "XSMO": 82.47,
    "SOFI": 18.785,
    "GOOGL": 336.34,
    "V": 316.07293,
    "UBER": 77.765,
    "MSFT": 412.12,
    "HD": 338.65,
    "SMH": 451.3919,
    "APLD": 30.2929,
    "RGTI": 19.005,
    "AIQ": 52.701,
    "VRT": 300.18,
    "QTUM": 123.21,
    "ANET": 153.565,
    "CRDO": 168.29,
    "QBTS": 20.44,
    "SE": 90.8,
    "DFAE": 36.975,
    "DFAU": 48.36
  },
  "missing": [
    "LITM",
    "LITM"
  ]
}